Metadata-Version: 2.1
Name: pygdal
Version: 3.8.2.12
Summary: Virtualenv and setuptools friendly version of standard GDAL python bindings
Home-page: https://github.com/nextgis/pygdal
Author: Frank Warmerdam
Author-email: warmerdam@pobox.com
Maintainer: Aleksandr Dezhin
Maintainer-email: me@dezhin.net
License: MIT
Classifier: Development Status :: 5 - Production/Stable
Classifier: Intended Audience :: Developers
Classifier: Intended Audience :: Science/Research
Classifier: License :: OSI Approved :: MIT License
Classifier: Operating System :: OS Independent
Classifier: Programming Language :: Python :: 2
Classifier: Programming Language :: Python :: 3
Classifier: Programming Language :: C
Classifier: Programming Language :: C++
Classifier: Topic :: Scientific/Engineering :: GIS
Classifier: Topic :: Scientific/Engineering :: Information Analysis
Requires-Python: >=3.6
Requires-Dist: numpy>=1.0.0
